LinkedinAutomation/__init__.py
LinkedinAutomation/main.py
LinkedinAutomation-0.1.dist-info/LICENSE
LinkedinAutomation-0.1.dist-info/METADATA
LinkedinAutomation-0.1.dist-info/WHEEL
LinkedinAutomation-0.1.dist-info/top_level.txt
LinkedinAutomation-0.1.dist-info/RECORD
