Metadata-Version: 2.1
Name: LinkedinAutomation
Version: 0.1
Summary: A Python package for remove unwanted linkedin connection.
Author: Ranjeet Aloriya
Author-email: ranjeet.aloriya@gmail.com
Keywords: breach response,breach notification,notification lists,data consolidation,unique identifiers,affected parties,data merging,efficiency tools,duplicate notifications incident response,document review,data consolidation,unique identifiers,affected parties,data merging,efficiency tools,duplicate notifications,incident response,breach response
Classifier: Programming Language :: Python :: 3
Classifier: License :: OSI Approved :: MIT License
Classifier: Operating System :: OS Independent
Classifier: Development Status :: 5 - Production/Stable
Classifier: Intended Audience :: Developers
Classifier: Topic :: Software Development :: Libraries :: Python Modules
Classifier: Natural Language :: English
Classifier: Environment :: Console
Requires-Python: >=3.6
License-File: LICENSE
Requires-Dist: datetime
Requires-Dist: pandas
Requires-Dist: numpy
Requires-Dist: pyGithub
Requires-Dist: polars
Requires-Dist: selenium
Requires-Dist: python-dotenv
